odoo/addons/sale_blanket_order_send/LICENSE
odoo/addons/sale_blanket_order_send/README.rst
odoo/addons/sale_blanket_order_send/__init__.py
odoo/addons/sale_blanket_order_send/__manifest__.py
odoo/addons/sale_blanket_order_send/data/mail_data.xml
odoo/addons/sale_blanket_order_send/i18n/de.po
odoo/addons/sale_blanket_order_send/images/screen.png
odoo/addons/sale_blanket_order_send/models/__init__.py
odoo/addons/sale_blanket_order_send/models/blanket_order.py
odoo/addons/sale_blanket_order_send/static/description/icon.png
odoo/addons/sale_blanket_order_send/static/description/index.html
odoo/addons/sale_blanket_order_send/tests/TEST_INSTRUCTIONS.rst
odoo/addons/sale_blanket_order_send/views/sale_blanket_order.xml
odoo_addon_sale_blanket_order_send-16.0.1.0.0.dist-info/METADATA
odoo_addon_sale_blanket_order_send-16.0.1.0.0.dist-info/WHEEL
odoo_addon_sale_blanket_order_send-16.0.1.0.0.dist-info/top_level.txt
odoo_addon_sale_blanket_order_send-16.0.1.0.0.dist-info/RECORD
