Metadata-Version: 2.1
Name: odoo-addon-sale_blanket_order_send
Version: 16.0.1.0.0
Requires-Python: >=3.10
Requires-Dist: odoo-addon-sale_blanket_order_date_confirmed>=16.0dev,<16.1dev
Requires-Dist: odoo>=16.0a,<16.1dev
Summary: Send blanket order by e-mail.
Home-page: https://www.mint-system.ch/
License: AGPL-3
Author: Mint System GmbH
Classifier: Programming Language :: Python
Classifier: Framework :: Odoo
Classifier: Framework :: Odoo :: 16.0
Classifier: License :: OSI Approved :: GNU Affero General Public License v3
